fastoas/__init__.py
fastoas/const/__init__.py
fastoas/const/fastapi.py
fastoas/const/pydantic.py
fastoas/const/specification.py
fastoas/const/symbols.py
fastoas/extensions/__init__.py
fastoas/extensions/affix/__init__.py
fastoas/extensions/affix/handlers.py
fastoas/extensions/errors/__init__.py
fastoas/extensions/errors/exceptions.py
fastoas/extensions/errors/utils.py
fastoas/extensions/operationid/__init__.py
fastoas/extensions/operationid/handlers.py
fastoas/utils/__init__.py
fastoas/utils/specification.py
tests/__init__.py
tests/test_init.py
fastoas-0.0.1.dist-info/LICENSE
fastoas-0.0.1.dist-info/METADATA
fastoas-0.0.1.dist-info/WHEEL
fastoas-0.0.1.dist-info/top_level.txt
fastoas-0.0.1.dist-info/RECORD
